{
    "got": 7.333333333333333,
    "cold": 9.333333333333334,
    "sweet": 8.333333333333334,
    "rate_count": 3,
    "courseInfo": {
        "id": "10527",
        "系所名稱": "大學國文 CL",
        "系號": "A7",
        "選課序號": "A7037",
        "課程碼": "A715600",
        "分班碼": "4",
        "班別": "",
        "年級": "1",
        "類別": "大學國文",
        "組別": null,
        "英語授課": "N",
        "課程名稱": "大學國文-現代文學與文化",
        "選必修": "必修",
        "學分": 2,
        "老師": "李京珮",
        "已選課人數": 0,
        "餘額": 50,
        "時間": "[4]7~8 ",
        "教室": "數學系館 3172",
        "備註": "",
        "限選條件": "",
        "業界參與": "否",
        "屬性碼": "CL1032",
        "跨領域學分學程": "",
        "Moocs": "否",
        "updateTime": null,
        "comment_num": 2,
        "remain_update_time": "2022-07-17T00:27:21.000Z",
        "count": 915,
        "admit": null,
        "comment": 3,
        "course_style": 0,
        "report_hw": 0,
        "score_style": 0,
        "semester": null
    },
    "comment": [
        {
            "id": 8722,
            "comment": "上課很輕鬆，聽老師講故事。\n期中期末是短文閱讀後二到四百字的賞析，老師短文會提前兩個禮拜給，時間很充裕。\n總體是分數好又可以淺嚐一些現代文學的好課!",
            "semester": "110-1"
        },
        {
            "id": 8586,
            "comment": "上課都在聽老師說文本，老師上課也蠻有趣的，期中期末上傳400字的小作業就好\n最後90分過\n\n成績分布\n90-100:20\n80-90:34\n70-80:4\n60-70:1\n50-60:1",
            "semester": "110-1"
        },
        {
            "id": 8918,
            "comment": "我那學期是全線上，即便說可以實體了還是可以線上，而且在期中考周還直接放假，真的超涼\n而且老師本人人很好，而且又年輕，整學期只交了3個心得而已，都400字以內。",
            "semester": "110-1"
        }
    ],
    "rates": [
        {
            "id": 5799,
            "got": 8,
            "sweet": 8,
            "cold": 10,
            "user_id": 6625,
            "post_id": 8586,
            "course_name": "大學國文-現代文學與文化",
            "teacher": "李京珮",
            "like": 0,
            "dislike": 0,
            "give": 1,
            "recommand": 1,
            "hard": 1
        },
        {
            "id": 5935,
            "got": 8,
            "sweet": 10,
            "cold": 8,
            "user_id": 5598,
            "post_id": 8722,
            "course_name": "大學國文-現代文學與文化",
            "teacher": "李京珮",
            "like": 0,
            "dislike": 0,
            "give": 1,
            "recommand": 1,
            "hard": 1
        },
        {
            "id": 6131,
            "got": 6,
            "sweet": 7,
            "cold": 10,
            "user_id": 8398,
            "post_id": 8918,
            "course_name": "大學國文-現代文學與文化",
            "teacher": "李京珮",
            "like": 0,
            "dislike": 0,
            "give": 1,
            "recommand": 1,
            "hard": 1
        }
    ],
    "courserate_id": 0
}