{
    "got": "0.0",
    "cold": "0.0",
    "sweet": "0.0",
    "rate_count": 0,
    "courseInfo": {
        "id": "331",
        "系所名稱": "通識中心 GE",
        "系號": "A9",
        "選課序號": "A9013",
        "課程碼": "A92L000",
        "分班碼": "",
        "班別": "",
        "年級": "",
        "類別": "人文學",
        "組別": null,
        "英語授課": "N",
        "課程名稱": "戲劇製作",
        "選必修": "必修",
        "學分": 2,
        "老師": "胡紫雲",
        "已選課人數": 17,
        "餘額": 3,
        "時間": "[1]5~6 ",
        "教室": "中文系館 21X06",
        "備註": "",
        "限選條件": "",
        "業界參與": "否",
        "屬性碼": "GE2183",
        "跨領域學分學程": "戲劇學程",
        "Moocs": "否",
        "updateTime": null,
        "comment_num": 0,
        "remain_update_time": "2022-07-03T22:44:27.000Z",
        "count": 1234,
        "admit": null,
        "comment": 0,
        "course_style": 0,
        "report_hw": 0,
        "score_style": 0
    },
    "comment": [],
    "rates": [],
    "courserate_id": 0
}