{
    "got": "7.0",
    "cold": "10.0",
    "sweet": "8.0",
    "rate_count": 1,
    "courseInfo": {
        "id": "327",
        "系所名稱": "通識中心 GE",
        "系號": "A9",
        "選課序號": "A9009",
        "課程碼": "A92P500",
        "分班碼": "",
        "班別": "",
        "年級": "",
        "類別": "人文學",
        "組別": null,
        "英語授課": "N",
        "課程名稱": "電影藝術與生活",
        "選必修": "必修",
        "學分": 2,
        "老師": "馬薇茜",
        "已選課人數": 83,
        "餘額": 7,
        "時間": "[3]3~4 ",
        "教室": "土木系館 4509",
        "備註": "",
        "限選條件": "",
        "業界參與": "否",
        "屬性碼": "GE2022",
        "跨領域學分學程": "戲劇學程",
        "Moocs": "否",
        "updateTime": null,
        "comment_num": 1,
        "remain_update_time": "2022-06-09T11:23:22.000Z",
        "count": 4954,
        "admit": null,
        "comment": 0,
        "course_style": 0,
        "report_hw": 0,
        "score_style": 0
    },
    "comment": [
        {
            "id": 7744,
            "comment": "上課形式：每堂課都會來看一部電影、或是請電影主題相關人士來進行演講。聽完演講之後至少會給一個禮拜的時間給你寫心得。\n\n點名：每堂點名\n\n心得：其中比較注意的是期末作業的部分。期末老師會要大家分組拍微電影，題材不拘，但必須與當學期的主題有呼應(109-2學期的主題是環境、關懷等等大範圍的主題)。分組方式自由，像我就是選擇自己一個人一組；但也有看到10人一組的。\n\n若是對電影有興趣，想要每個禮拜看一部電影的同學，我非常推薦這一門課。\n\n這學期看了： 為了與你相遇、平成貍合戰、十二夜\n\n評分標準：\n出席\t    20%\n期中考\t    15%\n個人書面報告 15%\n平時測驗     20%\n作業         30%\n\n以我的經驗，我的心得作業通常至少800字以上，且附圖，微電影最後的評價也不錯；學期成績89分作收。\n\n\n老師：\n\n馬薇茜老師非常親切，而且上課風格非常自由，再出作業時都會盡量考慮學生的復旦及創作自由。我認為是個非常棒的老師！",
            "semester": "109-2"
        }
    ],
    "rates": [
        {
            "id": 4994,
            "got": 7,
            "sweet": 8,
            "cold": 10,
            "user_id": 6374,
            "post_id": 7744,
            "course_name": "電影藝術與生活",
            "teacher": "馬薇茜",
            "like": 0,
            "dislike": 0,
            "give": 1,
            "recommand": 1,
            "hard": 1
        }
    ],
    "courserate_id": 0
}