{
    "got": 8.428571428571429,
    "cold": 6.642857142857143,
    "sweet": 8.5,
    "rate_count": 14,
    "courseInfo": {
        "id": "12929",
        "系所名稱": "通識中心 GE",
        "系號": "A9",
        "選課序號": "A9600",
        "課程碼": "A92M500",
        "分班碼": "",
        "班別": "",
        "年級": "",
        "類別": "自然與工程科學",
        "組別": null,
        "英語授課": "N",
        "課程名稱": "拍出跨域資訊應用首部曲--python",
        "選必修": "必修",
        "學分": 1,
        "老師": "陳培殷",
        "已選課人數": 112,
        "餘額": 28,
        "時間": "",
        "教室": "",
        "備註": "上課方式與時間請參見課程大綱。限非工學院及電資學院學生修習。",
        "限選條件": "限跨院之學位學程／文學院／理學院／管理學院／醫學院／社會科學院／規劃與設計學院／生物科學與科技學院",
        "業界參與": "否",
        "屬性碼": "GE2614",
        "跨領域學分學程": "",
        "Moocs": "否",
        "updateTime": null,
        "comment_num": 13,
        "remain_update_time": "2023-10-23T07:26:36.000Z",
        "count": 2274,
        "admit": null,
        "created_time": "2023-06-16T18:33:58.000Z",
        "comment": 14,
        "course_style": 0,
        "report_hw": 0,
        "score_style": 0,
        "semester": null
    },
    "comment": [
        {
            "id": 9808,
            "comment": "一次四小時，兩個周末一個平日教完的\n\n老師教得非常非常仔細也非常好理解，而且老師人也很好一直叫助教題目改簡單改配分，零基礎的人完全可以來修，我就是完全零基礎的人\n\n每次上完都有回家作業和上機考試，上機考試雖然助教適宣稱和昨天作業考差不多的東西，但我個人覺得差蠻多的，第一次後的考試都會有一題左右很燒腦的題目，不過不用擔心，因為教授人真的很好基本分都改成至少九十，你只要上課有聽懂回家自己碰一下電腦基本上九十都不會有問題。\n\n上課內容以迴圈和IF為重，有三堂都在講迴圈吧，除了最後一堂課因為快上不完了教授用飆的我沒聽懂外其他天的課都很好理解吸收，有點涼但建議不要不聽，因為教授真的教得很好也教得很滿\n然後上課有很多助教，舉手就會過來幫你，助叫人也都很NICE都會慢慢解析給你聽，作業寫不出來也可以提前來教室問助教\n\n分數超級甜(基本分都有拿到的前提下)\n\n總而言之就是一堂好課!收穫滿滿 全部上完課的那天心情真的很好很滿足 趕快來修!!!",
            "semester": "112-1"
        },
        {
            "id": 9246,
            "comment": "上課時間：開學的前兩週週末下午3-4個小時左右。最後一次是平日晚上。\n\n上課內容：很基礎的python語言，我之前沒有學過類似課程也大致聽得懂，但因為時間有限所以只能學一點點入門，如果真的想學很深的內容，建議選那種一整個學期的課。\n\n上課方式：老師會給一段時間讓大家自己看影片，然後出個隨堂練習的東西，時間到給助教檢查順便點名，因為是自己看影片也可以自己調倍速:D，我自己是調1.5在看的。\n\n計分方式：每次上完課會出作業，都是上課的東西，通常一個小時內可以寫完，考試通常也跟作業有點關係。學期成績是4次作業+四次考試+點名。個人覺得前三次考試都跟作業差不多很好寫，但最後一次考試超難，我只考40。最後學期成績91過。\n",
            "semester": "110-1"
        },
        {
            "id": 8358,
            "comment": "教很基礎的程式語言，線上上課，為密集課程，在兩周的周末下午還有一天的平日晚上，上課時看一段影片，然後參與線上會議室，會點名，每一個會議室約6位，第2~5次下課前有線上考試，要開鏡頭，10月初就結束課程了。\n\n作業很容易拿到100分，考試第一次和第二次也是。\n\n評分:4次作業(40%)+4次課堂線上考試(60%)\n分數甜，最後9X過，也有人拿到100",
            "semester": "110-1"
        },
        {
            "id": 8047,
            "comment": "上課形式\n很多助教在旁邊，教授教範例的時候會讓同學也練一些例題，有問題儘管問助教，\n雖然他們都很厲害但態度都很好不會讓人覺得彆扭或不敢問。\n\n學習內容\n就很皮毛的python，對程式有點興趣而不知從何下手的初學者很適合。\n\n作業\n滿簡單的我都100分，記得自己多run過幾次。\n\n其他\n分組報告不要太敷衍!\n分數滿甜的 最後92過",
            "semester": "109-2"
        },
        {
            "id": 7618,
            "comment": "非常適合初學者來上課，老師講解的很詳細，作業考試都很簡單\n分組報告只有稍微改一下現有的程式碼就好，而且每組都會派助教來協助",
            "semester": "109-1"
        },
        {
            "id": 6767,
            "comment": "老師上課教的很詳細，課堂小考也不難（開書考），只要會老師上課講的就可以拿高分。期末是一份小組報告，只要小修改助教已經完成的程式即可，不難又能學到東西，適合初學者",
            "semester": "108-1"
        },
        {
            "id": 5203,
            "comment": "兩個周末上課加上一個晚上報告專題，一開始上的內容很基本步調也很慢，但第二周就變得很趕，作業也是第一周很簡單第二周很難，專題也有點麻煩，如果真的要說優點的話就是分數給很高，建議選這門課前要再考慮一下",
            "semester": "107-2"
        },
        {
            "id": 6337,
            "comment": "完全不需要程式基礎的好課！老師會從最簡單的操作和語法教起，最後有一個團體作業、中間有兩次個人作業，不過後期教不太完所以理解起來會比較吃力，但還是值得一上的好課！",
            "semester": "107-2"
        },
        {
            "id": 5109,
            "comment": "連續兩個星期六上課整天，最後在某個星期二報告期末小組作業\n老師邊講邊練習，有很對助教可以問，不擔心不會但沒人問\n不難懂，但我後面1/5比較不太懂，最後的小組作業是用助教已經寫好的程式，三選一，去改，基本上助教都寫好了，我們要改的不是技術上的程式碼，主要是把整個美化，改字體和照片等等，還有自己的主題，例如:有一個軟體是搜尋，那小組要討論要做台南美食，臺南古蹟還是什麼，最好有創意\n算是對程式這個領域的初步認識，了解一些邏輯。\n期末87分\n",
            "semester": "107-2"
        },
        {
            "id": 4619,
            "comment": "密集課程，收穫不大，分數很甜，上課會教最基本的python語言而已，會寫2-3個簡單的python程式當作業。最後會提供完整程式給同學去做修改或改良，然後上台報告來說明你對程式改良。",
            "semester": "107-1"
        },
        {
            "id": 4325,
            "comment": "因為是短期課程\n原則上全部都要出席\n\n上課的內容很少\n最開始基礎的部分老師上的很慢\n沒有程式基礎的人也很容易懂\n但到後期因為要留時間讓大家報告\n後期需要花時間學的部分反而上的很趕\n\n然後期末成績主要是根據期末報告去給分\n因為學到的東西很少也很基本\n其實很難做出什麼成果\n所以大家的分數也差不多\n大部分都8或9開頭\n\n有程式基礎的人應該會覺得很涼很簡單\n沒程式基礎的人應該也不會覺得負擔太重\n因為時間很短\n其實也學不了很多\n",
            "semester": "107-1"
        },
        {
            "id": 3567,
            "comment": "分組的部分蠻多的，建議大家找朋友一起修，也能比較快解決不懂的地方～\n（我是一開始選課選到的，不過後來助教有寄信說開放加簽）\n\n老師講解得很清楚，沒碰過程式的人也可以上手\n而且有很多位助教，有什麼問題都能直接舉手發問\n上課講義也編寫得很清楚，我最近拿起來複習（？）都還能很快地回想起來\n\n個人覺得是一門很適合新手入門的課～",
            "semester": "107-1"
        },
        {
            "id": 4344,
            "comment": "開學之後可以加簽，送單子就簽那種。(加簽第一堂一定要去)\n\n很簡單的python入門，教一些print啊if啊while迴圈for迴圈之類的，覺得可以稍微訓練一下邏輯\n老師上課講解都很清楚，還會印講義給大家(ppt)，我覺得是沒學過程式語言可以輕鬆入門的好課~\n\n基本上作業細心做都可以拿到滿分，分組報告有用心做大家其實分數都不會差太多。\n分數給得很集中幾乎都89~94(不過倒是沒有人拿95以上)\n總之很推~",
            "semester": "107-1"
        },
        {
            "id": 3433,
            "comment": "這堂課的設定是給非資訊背景的人也可以學寫python\n我覺得陳培殷老師真的很會教，能夠以白話文的方式去解釋程式語言\n上課期間也可以處處感受到他的認真跟用心\n上課過程也有很多助教讓同學發問\n想入門程式語言的同學這堂課是你的好選擇！\n",
            "semester": "106-1"
        }
    ],
    "rates": [
        {
            "id": 852,
            "got": 9,
            "sweet": 7,
            "cold": 4,
            "user_id": 1884,
            "post_id": 3433,
            "course_name": "拍出跨域資訊應用首部曲--python",
            "teacher": "陳培殷",
            "like": 0,
            "dislike": 0,
            "give": 1,
            "recommand": 1,
            "hard": 1
        },
        {
            "id": 986,
            "got": 9,
            "sweet": 9,
            "cold": 8,
            "user_id": 1938,
            "post_id": 3567,
            "course_name": "拍出跨域資訊應用首部曲--python",
            "teacher": "陳培殷",
            "like": 0,
            "dislike": 0,
            "give": 1,
            "recommand": 1,
            "hard": 1
        },
        {
            "id": 1744,
            "got": 5,
            "sweet": 8,
            "cold": 8,
            "user_id": 2183,
            "post_id": 4325,
            "course_name": "拍出跨域資訊應用首部曲--python",
            "teacher": "陳培殷",
            "like": 0,
            "dislike": 0,
            "give": 1,
            "recommand": 1,
            "hard": 1
        },
        {
            "id": 1763,
            "got": 8,
            "sweet": 9,
            "cold": 8,
            "user_id": 1441,
            "post_id": 4344,
            "course_name": "拍出跨域資訊應用首部曲--python",
            "teacher": "陳培殷",
            "like": 0,
            "dislike": 0,
            "give": 1,
            "recommand": 1,
            "hard": 1
        },
        {
            "id": 2038,
            "got": 3,
            "sweet": 8,
            "cold": 4,
            "user_id": 2352,
            "post_id": 4619,
            "course_name": "拍出跨域資訊應用首部曲--python",
            "teacher": "陳培殷",
            "like": 0,
            "dislike": 0,
            "give": 1,
            "recommand": 1,
            "hard": 1
        },
        {
            "id": 2480,
            "got": 10,
            "sweet": 6,
            "cold": 2,
            "user_id": 1111,
            "post_id": 5109,
            "course_name": "拍出跨域資訊應用首部曲--python",
            "teacher": "陳培殷",
            "like": 0,
            "dislike": 0,
            "give": 1,
            "recommand": 1,
            "hard": 1
        },
        {
            "id": 2574,
            "got": 6,
            "sweet": 10,
            "cold": 9,
            "user_id": 329,
            "post_id": 5203,
            "course_name": "拍出跨域資訊應用首部曲--python",
            "teacher": "陳培殷",
            "like": 0,
            "dislike": 0,
            "give": 1,
            "recommand": 1,
            "hard": 1
        },
        {
            "id": 3708,
            "got": 10,
            "sweet": 7,
            "cold": 7,
            "user_id": 1682,
            "post_id": 6337,
            "course_name": "拍出跨域資訊應用首部曲--python",
            "teacher": "陳培殷",
            "like": 0,
            "dislike": 0,
            "give": 1,
            "recommand": 1,
            "hard": 1
        },
        {
            "id": 4138,
            "got": 10,
            "sweet": 8,
            "cold": 5,
            "user_id": 1728,
            "post_id": 6767,
            "course_name": "拍出跨域資訊應用首部曲--python",
            "teacher": "陳培殷",
            "like": 0,
            "dislike": 0,
            "give": 1,
            "recommand": 1,
            "hard": 1
        },
        {
            "id": 4868,
            "got": 10,
            "sweet": 10,
            "cold": 10,
            "user_id": 2519,
            "post_id": 7618,
            "course_name": "拍出跨域資訊應用首部曲--python",
            "teacher": "陳培殷",
            "like": 0,
            "dislike": 0,
            "give": 1,
            "recommand": 1,
            "hard": 1
        },
        {
            "id": 5260,
            "got": 10,
            "sweet": 10,
            "cold": 6,
            "user_id": 6200,
            "post_id": 8047,
            "course_name": "拍出跨域資訊應用首部曲--python",
            "teacher": "陳培殷",
            "like": 0,
            "dislike": 0,
            "give": 1,
            "recommand": 1,
            "hard": 1
        },
        {
            "id": 5571,
            "got": 10,
            "sweet": 9,
            "cold": 8,
            "user_id": 8066,
            "post_id": 8358,
            "course_name": "拍出跨域資訊應用首部曲--python",
            "teacher": "陳培殷",
            "like": 0,
            "dislike": 0,
            "give": 1,
            "recommand": 1,
            "hard": 1
        },
        {
            "id": 6459,
            "got": 8,
            "sweet": 9,
            "cold": 8,
            "user_id": 5883,
            "post_id": 9246,
            "course_name": "拍出跨域資訊應用首部曲--python",
            "teacher": "陳培殷",
            "like": 0,
            "dislike": 0,
            "give": 1,
            "recommand": 1,
            "hard": 1
        },
        {
            "id": 7021,
            "got": 10,
            "sweet": 9,
            "cold": 6,
            "user_id": 11091,
            "post_id": 9808,
            "course_name": "拍出跨域資訊應用首部曲--python",
            "teacher": "陳培殷",
            "like": 0,
            "dislike": 0,
            "give": 1,
            "recommand": 1,
            "hard": 1
        }
    ],
    "courserate_id": 0
}