{
    "got": "7.0",
    "cold": "10.0",
    "sweet": "7.0",
    "rate_count": 1,
    "courseInfo": {
        "id": "572",
        "系所名稱": "中文系 CL",
        "系號": "B1",
        "選課序號": "B1060",
        "課程碼": "B124800",
        "分班碼": "",
        "班別": "",
        "年級": "2",
        "類別": "講義",
        "組別": null,
        "英語授課": "N",
        "課程名稱": "社會語言學",
        "選必修": "選修",
        "學分": 2,
        "老師": "陳菘霖",
        "已選課人數": 56,
        "餘額": 5,
        "時間": "[2]5~6 ",
        "教室": "中文系館 21302",
        "備註": "",
        "限選條件": "",
        "業界參與": "否",
        "屬性碼": "CL3065",
        "跨領域學分學程": "",
        "Moocs": "否",
        "updateTime": null,
        "comment_num": 1,
        "remain_update_time": "2022-05-29T21:11:12.000Z",
        "count": 579,
        "admit": null,
        "comment": 0,
        "course_style": 0,
        "report_hw": 0,
        "score_style": 0
    },
    "comment": [
        {
            "id": 7216,
            "comment": "老師上課會先帶大家導讀過社會學實驗相關的書籍，各組則會分配到一篇論文分次報告，真的想初步認識社語的人非常推薦！老師人幽默又曾是補習班名師，講解很清楚～～",
            "semester": "108-2"
        }
    ],
    "rates": [
        {
            "id": 4466,
            "got": 7,
            "sweet": 7,
            "cold": 10,
            "user_id": 5113,
            "post_id": 7216,
            "course_name": "社會語言學",
            "teacher": "陳菘霖",
            "like": 0,
            "dislike": 0,
            "give": 1,
            "recommand": 1,
            "hard": 1
        }
    ],
    "courserate_id": 0
}