{
    "got": "0.0",
    "cold": "0.0",
    "sweet": "0.0",
    "rate_count": 0,
    "courseInfo": {
        "id": "596",
        "系所名稱": "外文系 FLL",
        "系號": "B2",
        "選課序號": "B2008",
        "課程碼": "B210611",
        "分班碼": "2",
        "班別": "",
        "年級": "1",
        "類別": "講義",
        "組別": null,
        "英語授課": "Y",
        "課程名稱": "英語口語訓練（一）",
        "選必修": "必修",
        "學分": 3,
        "老師": "廖培真",
        "已選課人數": 0,
        "餘額": 0,
        "時間": "[3]2 [5]3~4 ",
        "教室": "修齊大樓 26406",
        "備註": "Ｂ組，限本系",
        "限選條件": "限本系",
        "業界參與": "否",
        "屬性碼": "FLL1103E",
        "跨領域學分學程": "",
        "Moocs": "否",
        "updateTime": null,
        "comment_num": 0,
        "remain_update_time": "2021-08-13T21:51:14.000Z",
        "count": 8,
        "admit": null,
        "comment": 0,
        "course_style": 0,
        "report_hw": 0,
        "score_style": 0
    },
    "comment": [],
    "rates": [],
    "courserate_id": 0
}