{
    "got": "8.5",
    "cold": "3.0",
    "sweet": "6.5",
    "rate_count": 2,
    "courseInfo": {
        "id": "654",
        "系所名稱": "歷史系 HIS",
        "系號": "B3",
        "選課序號": "B3069",
        "課程碼": "B339000",
        "分班碼": "",
        "班別": "",
        "年級": "2",
        "類別": "講義",
        "組別": null,
        "英語授課": "Y",
        "課程名稱": "人與動物關係史",
        "選必修": "選修",
        "學分": 2,
        "老師": "李鑑慧",
        "已選課人數": 0,
        "餘額": 25,
        "時間": "[4]3~4 ",
        "教室": "歷史系館 25129",
        "備註": "世，英語授課",
        "限選條件": "第一階段不受理選課",
        "業界參與": "否",
        "屬性碼": "HIS3027",
        "跨領域學分學程": "",
        "Moocs": "否",
        "updateTime": null,
        "comment_num": 1,
        "remain_update_time": "2022-06-26T22:31:21.000Z",
        "count": 124,
        "admit": null,
        "comment": 0,
        "course_style": 0,
        "report_hw": 0,
        "score_style": 0
    },
    "comment": [
        {
            "id": 4374,
            "comment": "平時分數30%(課堂參與、發言)\n個人作業40%(讀書心得+講座心得)\n團體報告30%\n\n\n整體來說\n上課題材很少見\n會引起很多思考\n最有負擔的部分是團體報告\n形式是辯論會那種\n除了蒐集資料之外還要去說服大家\n需要很多練習\n也要花時間去跟對方質詢內容\n但一學期下來，真的有所收穫\n對於動物保護議題有興趣很推薦這門課\n\n",
            "semester": "107-1"
        },
        {
            "id": 7271,
            "comment": "這堂是英語授課，也有一些外籍生，但用字都不會太難，只是說話或交作業\n需要用英文可能比較麻煩。\n作業跟報告整體都偏硬，有興趣了解的人可以找老師要講義(老師人很nice\n的)，上面會寫時程表以及要交的作業規定等。\n如果對這堂課有興趣卻不想要有太多壓力的話可以考慮老師開的一堂通識\n課\"人、動物與倫理\"。\n",
            "semester": "107-1"
        }
    ],
    "rates": [
        {
            "id": 1793,
            "got": 10,
            "sweet": 7,
            "cold": 2,
            "user_id": 324,
            "post_id": 4374,
            "course_name": "人與動物關係史",
            "teacher": "李鑑慧",
            "like": 0,
            "dislike": 0,
            "give": 1,
            "recommand": 1,
            "hard": 1
        },
        {
            "id": 4521,
            "got": 7,
            "sweet": 6,
            "cold": 4,
            "user_id": 5935,
            "post_id": 7271,
            "course_name": "人與動物關係史",
            "teacher": "李鑑慧",
            "like": 0,
            "dislike": 0,
            "give": 1,
            "recommand": 1,
            "hard": 1
        }
    ],
    "courserate_id": 0
}