{
    "got": "9.0",
    "cold": "8.0",
    "sweet": "8.0",
    "rate_count": 1,
    "courseInfo": {
        "id": "1167",
        "系所名稱": "電機系 EE",
        "系號": "E2",
        "選課序號": "E2143",
        "課程碼": "E243300",
        "分班碼": "",
        "班別": "甲乙丙",
        "年級": "3",
        "類別": "講義",
        "組別": null,
        "英語授課": "N",
        "課程名稱": "電力電子學",
        "選必修": "選修",
        "學分": 3,
        "老師": "梁從主",
        "已選課人數": 52,
        "餘額": 38,
        "時間": "[1]7~9 ",
        "教室": "電機系館 92225",
        "備註": "",
        "限選條件": "",
        "業界參與": "否",
        "屬性碼": "EE4340",
        "跨領域學分學程": "",
        "Moocs": "否",
        "updateTime": null,
        "comment_num": 1,
        "remain_update_time": "2022-01-19T06:21:17.000Z",
        "count": 193,
        "admit": null,
        "comment": 0,
        "course_style": 0,
        "report_hw": 0,
        "score_style": 0
    },
    "comment": [
        {
            "id": 6302,
            "comment": "上課形式：教授用自製講義上課，期初時會問有誰要印上課講義，由助教統一印，講義的ppt不會放到網路上。\n\n課堂要求：每堂上課前教授會要求學生起立做伸展，避免學生上課想睡覺。\n\n學習內容：主要介紹二極體、電容及電感等的特性，並利用電感的伏秒平衡設計出各種converter(buck, boost, buck-boost等)，也會介紹snubber circuit、RLC等電路。\n\n評分標準：出席10%、作業5%、期中考(1次)35%、期末考35%、平時測驗15%。\n\n考試方式：閉書考。考試內容由上課講義裡出，考得有點細，因此若要拿高分的話要讀很熟。考試時很常出某一電路電感、電容等的電流波形變化，或要你解釋電路在各個mode裡是如何運作的。\n\n作業：約5次作業，內容有計算電流有效值、計算平均功率、Power Factor的計算，以及在穩態下各個converter的duty cycle、電容及電感值、各元件的電壓和電流波形等。\n\n修課成績：期中86、期末80，作業都有交，點名都有到，最後90過。",
            "semester": "107-1"
        }
    ],
    "rates": [
        {
            "id": 3673,
            "got": 9,
            "sweet": 8,
            "cold": 8,
            "user_id": 1948,
            "post_id": 6302,
            "course_name": "電力電子學",
            "teacher": "梁從主",
            "like": 0,
            "dislike": 0,
            "give": 1,
            "recommand": 1,
            "hard": 1
        }
    ],
    "courserate_id": 0
}