{
    "got": "9.0",
    "cold": "8.5",
    "sweet": "8.0",
    "rate_count": 2,
    "courseInfo": {
        "id": "1330",
        "系所名稱": "材料系 MSE",
        "系號": "E5",
        "選課序號": "E5115",
        "課程碼": "E536900",
        "分班碼": "1",
        "班別": "甲",
        "年級": "3",
        "類別": "講義",
        "組別": null,
        "英語授課": "N",
        "課程名稱": "材料機械性質",
        "選必修": "必修",
        "學分": 3,
        "老師": "劉浩志",
        "已選課人數": 50,
        "餘額": 0,
        "時間": "[2]7~8 [5]7 ",
        "教室": "材料新館 44203",
        "備註": "",
        "限選條件": "",
        "業界參與": "否",
        "屬性碼": "MSE3009",
        "跨領域學分學程": "生物科技學程",
        "Moocs": "否",
        "updateTime": null,
        "comment_num": 2,
        "remain_update_time": "2022-06-01T01:20:45.000Z",
        "count": 185,
        "admit": null,
        "comment": 0,
        "course_style": 0,
        "report_hw": 0,
        "score_style": 0
    },
    "comment": [
        {
            "id": 7477,
            "comment": "我很喜歡上老師的這堂課，不僅是教學的方式生動有趣，並慢慢引導著我們思考，還可以透過課堂撥放的影片和提供的閱讀資料學到很多日常生活中的知識，謝謝老師，希望之後還可以在上到老師的課。",
            "semester": "109-1"
        },
        {
            "id": 3176,
            "comment": "老師人很親切，上課輕鬆、超多影片，上課上起來很爽，可是會在課堂突然插進我們要學的主題，然後把重要的東西講一講，跳過蠻多東西的，老師重觀念，考試題目很靈活，上課有認真就差不多會寫，但考卷不是老師本人改的，所以分數給的不太公平有些偏頗，不過大致可以學到一些材料機械性質的應用與學問，還不錯。",
            "semester": "107-1"
        }
    ],
    "rates": [
        {
            "id": 595,
            "got": 8,
            "sweet": 6,
            "cold": 7,
            "user_id": 1776,
            "post_id": 3176,
            "course_name": "材料機械性質",
            "teacher": "劉浩志",
            "like": 0,
            "dislike": 0,
            "give": 1,
            "recommand": 1,
            "hard": 1
        },
        {
            "id": 4727,
            "got": 10,
            "sweet": 10,
            "cold": 10,
            "user_id": 3539,
            "post_id": 7477,
            "course_name": "材料機械性質",
            "teacher": "劉浩志",
            "like": 0,
            "dislike": 0,
            "give": 1,
            "recommand": 1,
            "hard": 1
        }
    ],
    "courserate_id": 0
}