{
    "got": "0.0",
    "cold": "0.0",
    "sweet": "0.0",
    "rate_count": 0,
    "courseInfo": {
        "id": 8194,
        "系所名稱": "土木系 CE",
        "系號": "E6",
        "選課序號": "E6162",
        "課程碼": "N663201",
        "分班碼": "",
        "班別": "甲乙",
        "年級": "4",
        "類別": "講義",
        "組別": null,
        "英語授課": "Y",
        "課程名稱": "商務寫作和溝通技巧",
        "選必修": "選修",
        "學分": 3,
        "老師": "陸喬克",
        "已選課人數": 11,
        "餘額": 0,
        "時間": "[2]6~8 ",
        "教室": "土木系館 209",
        "備註": "大碩合班，英語授課",
        "限選條件": "",
        "業界參與": "否",
        "屬性碼": "CE5322",
        "跨領域學分學程": "",
        "Moocs": "否",
        "updateTime": null,
        "comment_num": 0,
        "remain_update_time": "2022-01-21T00:17:23.000Z",
        "count": 14,
        "admit": null,
        "comment": 0,
        "course_style": 0,
        "report_hw": 0,
        "score_style": 0
    },
    "comment": [],
    "rates": [],
    "courserate_id": 0
}