{
    "got": 7.666666666666667,
    "cold": 8.666666666666666,
    "sweet": 8.666666666666666,
    "rate_count": 3,
    "courseInfo": {
        "id": "1559",
        "系所名稱": "都計系 UP",
        "系號": "F2",
        "選課序號": "F2058",
        "課程碼": "F246800",
        "分班碼": "",
        "班別": "",
        "年級": "2",
        "類別": "講義",
        "組別": null,
        "英語授課": "N",
        "課程名稱": "敷地計劃",
        "選必修": "選修",
        "學分": 2,
        "老師": "竇國昌",
        "已選課人數": 0,
        "餘額": 40,
        "時間": "[5]7~8 ",
        "教室": "都計系館 50204",
        "備註": "",
        "限選條件": "",
        "業界參與": "否",
        "屬性碼": "UP2404",
        "跨領域學分學程": "",
        "Moocs": "否",
        "updateTime": null,
        "comment_num": 2,
        "remain_update_time": "2022-07-07T05:32:45.000Z",
        "count": 177,
        "admit": null,
        "comment": 3,
        "course_style": 0,
        "report_hw": 0,
        "score_style": 0,
        "semester": null
    },
    "comment": [
        {
            "id": 8572,
            "comment": "上課方式：刷卡點名，老師上課放ppt，然後講滿多有趣的廢話的，可以做自己的事。上課偶爾有報告，但到底有沒有要看老師當天決定。有一次作業，不難時間也很充裕，沒有考試，學期末有一次校外參訪。\n\n評分方式：沒公布，但應該就是看報告跟作業然後再依出席微調。\n\n上課很涼，老師完全不管，他也很chill有時候上課大晚到或是接電話啥的，有時候講話滿好笑的。報告可能算是有一點點花時間，主要是在跟組員討論，然後可能一些分析或配置圖。我個人上課完全沒在聽，有全勤，報告跟作業都有認真做，最後93。成績分布9字頭佔大多數，算很甜了。",
            "semester": "110-1"
        },
        {
            "id": 8845,
            "comment": "老師人很好，上課內容很充實，會講很多空間設計的基本原則，然後和老師的實務經驗做連結，告訴你哪些東西的很重要，有在聽課收穫就會很多。作業有點多，但都不會太難，小組作業的話老師不會給太多規定，多在簡報後再跟同學檢討，但能在評論前做到老師要求的，可以得到較好的評價，成績也會比較。總之，作業內容要細心，簡報要簡潔有力。",
            "semester": "110-1"
        },
        {
            "id": 5954,
            "comment": "作業算多 上課時間多半都是作業簡報跟老師回饋\n有時候老師也會上點課 聽課的人很少 作業也跟上課內容有關\n從老師的回饋中可以獲得很多收穫\n作業都是組作業",
            "semester": "107-1"
        }
    ],
    "rates": [
        {
            "id": 3325,
            "got": 8,
            "sweet": 10,
            "cold": 10,
            "user_id": 2284,
            "post_id": 5954,
            "course_name": "敷地計劃",
            "teacher": "竇國昌",
            "like": 0,
            "dislike": 0,
            "give": 1,
            "recommand": 1,
            "hard": 1
        },
        {
            "id": 5785,
            "got": 6,
            "sweet": 9,
            "cold": 9,
            "user_id": 6243,
            "post_id": 8572,
            "course_name": "敷地計劃",
            "teacher": "竇國昌",
            "like": 0,
            "dislike": 0,
            "give": 1,
            "recommand": 1,
            "hard": 1
        },
        {
            "id": 6058,
            "got": 9,
            "sweet": 7,
            "cold": 7,
            "user_id": 8325,
            "post_id": 8845,
            "course_name": "敷地計劃",
            "teacher": "竇國昌",
            "like": 0,
            "dislike": 0,
            "give": 1,
            "recommand": 1,
            "hard": 1
        }
    ],
    "courserate_id": 0
}