{
    "got": "3.0",
    "cold": "3.0",
    "sweet": "6.0",
    "rate_count": 1,
    "courseInfo": {
        "id": 9021,
        "系所名稱": "航太系 AA",
        "系號": "F4",
        "選課序號": "F4171",
        "課程碼": "F443520",
        "分班碼": "4A",
        "班別": "",
        "年級": "4",
        "類別": "講義",
        "組別": null,
        "英語授課": "N",
        "課程名稱": "航太工程實作（二）",
        "選必修": "必修",
        "學分": 2,
        "老師": "葉思沂",
        "已選課人數": 17,
        "餘額": 9,
        "時間": "[4]1 ",
        "教室": "航太系館 5822",
        "備註": "1.無人飛行器設計與實作(二)。2.需先修上學期課程內容才可修下學期。3.需同一學年修畢。4.上、下學期不可更換組別上課。",
        "限選條件": "",
        "業界參與": "否",
        "屬性碼": "AA4694",
        "跨領域學分學程": "",
        "Moocs": "否",
        "updateTime": null,
        "comment_num": 1,
        "remain_update_time": "2022-01-21T00:17:19.000Z",
        "count": 1,
        "admit": null,
        "comment": 0,
        "course_style": 0,
        "report_hw": 0,
        "score_style": 0
    },
    "comment": [
        {
            "id": 6220,
            "comment": "老師授課，主要是講一些跟飛機設計相近的內容，但是飛機設計主要是在學習燃料為油料的飛機，實作的「無人機設計組」則是以「電飛機」為主。\n實作部分，下學期會要求設計好一架飛機並實際製作出來，需要完成概念設計、初步設計、細部設計、無人機實作，但因為電子裝配、飛機設計的結構部分，助教無詳細教學，所以沒有厲害的隊友的話就可以直接無限輪迴撞牆，最後需要將實際製作的飛機執行飛行任務（一次空機飛行、一次載較高密度重物飛行、一次載體積較大物品飛行），並依據飛行狀況給分。最後，飛機飛得好分數也會好，報告寫得再好影響有限。",
            "semester": "107-2"
        }
    ],
    "rates": [
        {
            "id": 3591,
            "got": 3,
            "sweet": 6,
            "cold": 3,
            "user_id": 345,
            "post_id": 6220,
            "course_name": "航太工程實作（二）",
            "teacher": "葉思沂",
            "like": 0,
            "dislike": 0,
            "give": 1,
            "recommand": 1,
            "hard": 1
        }
    ],
    "courserate_id": 0
}