{
    "got": "9.2",
    "cold": "6.2",
    "sweet": "6.8",
    "rate_count": 6,
    "courseInfo": {
        "id": "13532",
        "系所名稱": "資訊系 CSIE",
        "系號": "F7",
        "選課序號": "F7010",
        "課程碼": "F711110",
        "分班碼": "",
        "班別": "甲乙",
        "年級": "1",
        "類別": "講義",
        "組別": null,
        "英語授課": "N",
        "課程名稱": "程式設計（一）",
        "選必修": "必修",
        "學分": 3,
        "老師": "蔡孟勳",
        "已選課人數": 0,
        "餘額": 125,
        "時間": "[4]2~4 ",
        "教室": "共同教室 A1302",
        "備註": "額外實習課星期二5~8節, 可自由參加",
        "限選條件": "",
        "業界參與": "否",
        "屬性碼": "CSIE1001",
        "跨領域學分學程": "",
        "Moocs": "否",
        "updateTime": null,
        "comment_num": 6,
        "remain_update_time": "2023-06-16T19:36:09.000Z",
        "count": 1,
        "admit": null,
        "created_time": "2023-06-16T18:33:58.000Z",
        "comment": 0,
        "course_style": 0,
        "report_hw": 0,
        "score_style": 0
    },
    "comment": [
        {
            "id": 8552,
            "comment": "作業和期中期末都有點難到太過分，沒有什麼辨識度，感覺就只是助教在整人而已，老師教得算認真，想學東西可以選，但是考試可能會考到很無助，我最後84",
            "semester": "110-1"
        },
        {
            "id": 8871,
            "comment": "老師上的很好，對初學者而言，每週助教的練習題很有幫助。\n助教還會安排實習課，不會可以去問，但有時人很多，要等很久，蠻浪費時間的。\n考試有easy medium hard 各兩題。\n我都只有寫出前面四題，時間有點來不及。\n但期末會大調分，最後100過。",
            "semester": "110-1"
        },
        {
            "id": 7960,
            "comment": "本人不是本系生，是工資系大一的，以前有自學過一點，但是老本大概前3/5學期的內容而已，可以參考一下\n\n作業:\n每周都有3~4題作業，前半學期的作業都蠻簡單的，後面會開始有一些比較難的題目，有些題目超級麻煩，不寫分數其實也不會差太多，期限是期末考結束那天的12點。\n\n考試:\n期中跟期末都有三小時的上機考，不會很難拿分數，總共有六題，三種難度各兩題，越簡單的分數越高，分別是25,20,15分。我覺得難度普通，作業扎實自己寫一定可以考很高，不過考試的題目難度會比作業高一點，考試當下可能會緊張。\n\n點名:\n不會點名，我大概只有去實體教室上3次課，其他都是上網看老師錄的影片，超讚不用早上爬起來。實習課不會上課，就是去寫作業的，沒有去過所以不清楚。\n\n作業20% 期中35% 期末45% 教授好像是資工蠻有名望的老師，教得很好，算是很適合入門程式語言的課。\n最後學期成績85，期末因為跑太多活動沒有什麼時間讀，考低了。我覺得夠努力，段考考90不會不可能。\n\n另外我還有修過 數位系統導論  跟  程式設計(二) ，都蠻不錯的也不會太難，外系想接觸看看資工的可以上上看\n              [大二上必修]     [大一下必修]\n",
            "semester": "109-1"
        },
        {
            "id": 8740,
            "comment": "每個禮拜都有作業，一開始蠻簡單的，後面會慢慢增加難度，我整個學期只有少交一題\n有期中期末上機考 滿分120\n期中105 期末72\n時不時會有加分提供不在MOODLE，通常與上課內容沒有甚麼關係，Bonus式加總成績，可以好好把握\n92過",
            "semester": "109-1"
        },
        {
            "id": 8054,
            "comment": "[修課的建議]\n我是外系來修這堂課，過去有學過一點基礎的python，蠻推薦大家先稍微學過一點程式的基礎再來修這堂課，不然對於外系的人來說其實還蠻硬的，期中考之後的內容會大幅變難，退選的人也會越來越多。如果你是想要學程式的外系生，學校也有其他的課可以參考看看，像是每年暑假開的Coding-X，或是敏求學院的課。\n\n[上課、作業]\n這堂課不會點名，老師會把每個禮拜的上課錄影上傳到youtube，只有期中期末考是一定要到場的。這堂課有專屬的作業和考試平台，每個禮拜都會有作業，如果作業都有好好自己寫完跟理解，考試的分數就不會太難看。每個禮拜也會有助教的實習課，作業遇到困難可以去問。\n\n[分數]\n成績是作業20%，期中35%，期末45%，雖然作業的配分很少，不過寫作業真的很重要，把作業都好好寫完然後理解裡面的概念跟邏輯，除了作業的20%之外，期中期末應該也可以穩穩拿到分數。期中和期末考都是只有六題，簡單、中等、困難各兩題，但配分是簡單25分、中等20分、困難15分（總分超過一百），我自己作業幾乎都有寫完，考前只有稍微看一下課程ppt，簡單題跟中等題基本上就都解得出來，最後拿到的學期分數是87分。另外平常沒事可以多上moodle看看，會不定時出現一些奇怪的加分題。",
            "semester": "109-1"
        },
        {
            "id": 7893,
            "comment": "這堂課教C語言\n老師上課教得很好\n可以為程式新手打下非常扎實的基礎\n但每週作業對沒有程式經驗的人來說很難 (作業形式可以參考leetcode 差不多長那樣)\n課程時間為星期四 2~4節\n在下午5~~8為助教課時間\n課堂或作業有不懂的地方可以問助教(老師的研究生加上資工的醒獅團)\n助教都蠻好的，很熱心教你如何解決問題 \n但如果你直接跟助教說這題我不會，助教很大機率會無視並把你列入黑名單\n\n雖然說有助教幫忙，但這堂課還是建議找朋友組隊\n期中考之後課堂內容與作業會越來越難\n有沒有人一起討論差非常多\n\n課堂有一次期中考 一次期末考\n考題會出兩題簡單 兩題中等 兩題高等題目\n簡單題一題25分 中等20分 高等15分\n等於只要你能把兩題簡單題把握好，在加上答對一題中等題就能及格\n\n期中考是一個分水嶺\n作業在期中考之後會更有挑戰性\n如果期中考沒有超過60就可以考慮辦理退選\n\n在期末考之後班上人數會直線下降\n期初時教室座位被擠得水洩不通\n期中之後教室就會變得越來越冷清\n算是這堂課的特點\n\n",
            "semester": "109-1"
        }
    ],
    "rates": [
        {
            "id": 5143,
            "got": 9,
            "sweet": 4,
            "cold": 1,
            "user_id": 2126,
            "post_id": 7893,
            "course_name": "程式設計（一）",
            "teacher": "蔡孟勳",
            "like": 0,
            "dislike": 0,
            "give": 1,
            "recommand": 1,
            "hard": 1
        },
        {
            "id": 5210,
            "got": 10,
            "sweet": 8,
            "cold": 10,
            "user_id": 5958,
            "post_id": 7960,
            "course_name": "程式設計（一）",
            "teacher": "蔡孟勳",
            "like": 0,
            "dislike": 0,
            "give": 1,
            "recommand": 1,
            "hard": 1
        },
        {
            "id": 5267,
            "got": 9,
            "sweet": 7,
            "cold": 7,
            "user_id": 3419,
            "post_id": 8054,
            "course_name": "程式設計（一）",
            "teacher": "蔡孟勳",
            "like": 0,
            "dislike": 0,
            "give": 1,
            "recommand": 1,
            "hard": 1
        },
        {
            "id": 5765,
            "got": 7,
            "sweet": 4,
            "cold": 4,
            "user_id": 5263,
            "post_id": 8552,
            "course_name": "程式設計（一）",
            "teacher": "蔡孟勳",
            "like": 0,
            "dislike": 0,
            "give": 1,
            "recommand": 1,
            "hard": 1
        },
        {
            "id": 5953,
            "got": 10,
            "sweet": 8,
            "cold": 5,
            "user_id": 8183,
            "post_id": 8740,
            "course_name": "程式設計（一）",
            "teacher": "蔡孟勳",
            "like": 0,
            "dislike": 0,
            "give": 1,
            "recommand": 1,
            "hard": 1
        },
        {
            "id": 6084,
            "got": 10,
            "sweet": 10,
            "cold": 10,
            "user_id": 7539,
            "post_id": 8871,
            "course_name": "程式設計（一）",
            "teacher": "蔡孟勳",
            "like": 0,
            "dislike": 0,
            "give": 1,
            "recommand": 1,
            "hard": 1
        }
    ],
    "courserate_id": 0
}