{
    "got": "5.0",
    "cold": "7.5",
    "sweet": "7.5",
    "rate_count": 2,
    "courseInfo": {
        "id": "2014",
        "系所名稱": "醫學系 MED",
        "系號": "I5",
        "選課序號": "I5061",
        "課程碼": "I524700",
        "分班碼": "",
        "班別": "",
        "年級": "2",
        "類別": "講義",
        "組別": null,
        "英語授課": "N",
        "課程名稱": "性與生物史",
        "選必修": "選修",
        "學分": 2,
        "老師": "王秀雲*",
        "已選課人數": 37,
        "餘額": 6,
        "時間": "[1]7~8 ",
        "教室": "醫學院 302D",
        "備註": "醫學系「醫學人文課程」",
        "限選條件": "",
        "業界參與": "否",
        "屬性碼": "MED2402",
        "跨領域學分學程": "醫學、科技與社會學程(STM),性別研究學分學程,歷史與科技社會學分學程",
        "Moocs": "否",
        "updateTime": null,
        "comment_num": 3,
        "remain_update_time": "2022-06-02T03:13:17.000Z",
        "count": 328,
        "admit": null,
        "comment": 0,
        "course_style": 0,
        "report_hw": 0,
        "score_style": 0
    },
    "comment": [
        {
            "id": 5262,
            "comment": "老師人很好，講的東西也蠻有趣的，只是有時候不小心會被無聊到睡著，偶爾會覺得課程上某些東西一再重複，但是總體來說是一堂很棒的課！是性與生物史但不是兩性關係，甚至課程內容蠻質疑「兩」性的。有幾次小考，只要有看指定閱讀都寫得出來，老師的指定閱讀乍看之下很多但其實拆分成一個禮拜來看的話也還好，考試除了小考外只有期末考，老師會先公布題目而且開書考，作業也都不難大多是評論或是看法，只要你提出的論點有依據不是胡言亂語，即便跟老師的想法不同也不會怎樣，最後的分數是八十八，是一堂有收穫分數也不錯的課！",
            "semester": "107-2"
        },
        {
            "id": 5556,
            "comment": "【上課形式】\n\nPPT+討論\n\n【成績】\n\n10%出席\n15%上課提問\n20%閱讀短評*2\n15%小考*3\n40%期末\n\n【內容】\n\n雖說是醫學系選修，但上起來感覺比較像是通識，每堂點名，流程是事先閱讀老師發的文本，偶爾有小考考你有沒有讀(上周會提醒)，課堂先上一些先備知識，然後討論，偶爾會用影片結尾，沒有休息，會提早10分鐘下課，能睡覺能做自己的事。另外會有一堂課邀請雙性人來演講。\n\n【心得】\n\n基本上不硬，內容都是用文本來探討作者的觀點然後開始討論，文本大多淺顯易懂，由於觸碰的議題容易引發激烈辯論，適合喜歡唇槍舌戰的人去解解悶(誤)。\n\n短評大概花你半小時可以解決，小考我都前30分鐘抓重點讀，偶爾課堂發言和找老師辯論，最後83過",
            "semester": "107-2"
        },
        {
            "id": 2729,
            "comment": "這一堂課學到蠻多有關性別的內容! 主要在探討生物決定論、先天/後天、性別二元對立等議題，這些議題如何來造成性別的差異以及為何會有這些議題的產生(歷史脈絡)。而這學期講者是請到邱愛芝(雙性人)，來分享其心路歷程! \n\n非常極度建議課前先讀完指定閱讀短文，因為老師上課內容主要是跟同學互動，所以先讀完讀本的人比較能回答老師問題，或是提出問題(老師蠻注重這個的!)。而在互動的過程中，也會幫助自己學習到某些性別的觀念!\n\n若是對於性別議題有關注的人，或是通識有上過性別課程相關者，都蠻推薦來這堂課的! 雖然這堂課是醫學系選修，但是其實醫學知識蠻少的，所以很推薦外系來選修! 雖然這是我第一次接觸性別議題，但是其實內容不會太艱澀，只要在課堂多跟老師互動，就會學到蠻多東西的! \n\n老師人真的很好，考前都會提醒考試內容，如果對於申論題的題目不懂，也可以直接詢問老師，老師會跟你講大約內容以及提示!",
            "course_style": "老師上課會用投影片方式進行(偶爾看影片、請講者)，很常丟問題與台下同學共同討論",
            "course_need": "老師自己統整的講義(多篇文獻)",
            "exam_style": "1.小考: 考前一週，老師會上課提醒或在FB社團提醒下週小考\n              考試內容都是前幾週上課內容，題型有時是申論、選擇、想問老師的問\n              題，都是1題(上課開始就會發下去，10分鐘內要寫完並交卷，所以如果上\n              一節有課的人，要記得早一點到!否則只能另約補考時間@@ )\n2.期中、期末考，老師都會在考前一週發下申論題題目\n   期中:  選擇+申論+心得  \n              選擇都是上課教過的內容，申論則是從4題選2題考，\n               心得則是某次講者的心得內容\n   期末:  申論+加分題  \n              申論是從4題選1題考(期末可open book)，\n              加分題則是老師上課提及的文章做簡短的統整及自己的心得，文章題目老\n               師考前會給，但是要自己運用資源上網找",
            "semester": "106-1",
            "score_style": "出席10%、課程參與或提問或小考20%、期中考30%、期末考40% "
        }
    ],
    "rates": [
        {
            "id": 2633,
            "got": 6,
            "sweet": 8,
            "cold": 9,
            "user_id": 2101,
            "post_id": 5262,
            "course_name": "性與生物史",
            "teacher": "王秀雲*",
            "like": 0,
            "dislike": 0,
            "give": 1,
            "recommand": 1,
            "hard": 1
        },
        {
            "id": 2927,
            "got": 4,
            "sweet": 7,
            "cold": 6,
            "user_id": 1219,
            "post_id": 5556,
            "course_name": "性與生物史",
            "teacher": "王秀雲*",
            "like": 0,
            "dislike": 0,
            "give": 1,
            "recommand": 1,
            "hard": 1
        }
    ],
    "courserate_id": 0
}