{
    "got": "6.5",
    "cold": "7.9",
    "sweet": "8.8",
    "rate_count": 8,
    "courseInfo": {
        "id": "1999",
        "系所名稱": "醫學系 MED",
        "系號": "I5",
        "選課序號": "I5014",
        "課程碼": "I512900",
        "分班碼": "",
        "班別": "",
        "年級": "1",
        "類別": "講義",
        "組別": null,
        "英語授課": "Y",
        "課程名稱": "全球視野與溝通",
        "選必修": "選修",
        "學分": 2,
        "老師": "張雋曦*,張嘉倩,石明人,陳韻雯,橋本昌征,古鯉榕",
        "已選課人數": 0,
        "餘額": 26,
        "時間": "[5]7~8 ",
        "教室": "醫學院 203D",
        "備註": "醫學系「醫學人文課程」；於203D、208及醫圖210教室分組上課",
        "限選條件": "第一階段不受理選課；限醫學院",
        "業界參與": "否",
        "屬性碼": "MED1505E",
        "跨領域學分學程": "",
        "Moocs": "否",
        "updateTime": null,
        "comment_num": 8,
        "remain_update_time": "2022-01-19T00:18:55.000Z",
        "count": 228,
        "admit": null,
        "comment": 0,
        "course_style": 0,
        "report_hw": 0,
        "score_style": 0
    },
    "comment": [
        {
            "id": 7750,
            "comment": "每三個禮拜換一次老師，所以也次每三個禮拜就要交一次小組報告，全英授課，上課內容收穫確實不大，想認真學東西的同學要多加考慮，但課程輕鬆，重點是分數真的甜啊~",
            "semester": "109-2"
        },
        {
            "id": 7337,
            "comment": "老師都是用英語上課(不會太艱澀)\n活動都很有趣(如模擬賽車訓練，拆幽浮)\n運氣好的話可以在報告當天開童樂會\n這學期新增一位來自瑞典的老師，報告會看你有沒有用合格的來源\n除此之外都還蠻輕鬆的\n可以學到很多東西",
            "semester": "109-1"
        },
        {
            "id": 7346,
            "comment": "上課形式：老師授課+個報+團報\n\n評分：每一次的報告與課堂參與\n\n45個人會拆成三組，每組都是15人，在不同地方上課，之後就是這15人一直陪你到期末。這堂課很涼，可以交到朋友，或是跟同學會變熟。loading不會太重，可以調劑一下一個禮拜沈重的課業負擔。\n\n",
            "semester": "109-1"
        },
        {
            "id": 6847,
            "comment": "全英文授課，但不用太擔心自身英文程度不好。\n上課方式主要是以英文來討論或進行各種議題以及活動\n上課過程會有多次的討論和發表意見的機會，蠻有趣的，也能有練習說英文的機會。\n分數極甜，有作業上課要到，但不會帶來太多壓力。",
            "semester": "108-1"
        },
        {
            "id": 6629,
            "comment": "用全英文上課，每三堂課會oral presentation一次，不同的老師有不同的主題及報告形式，可以練習在一群醫學系的同學面前講英文。",
            "semester": "108-1"
        },
        {
            "id": 6441,
            "comment": "安東尼奧超讚 課好玩分數甜\n整體來說課好不好真的要看抽到哪幾個老師，有帶你去喝酒的(我沒遇到可惡)、有輕輕鬆鬆的，但是也有三堂課李耀報告兩次的(超雷)\n\n評分方式老師\n\n總分甜甜的",
            "semester": "107-2"
        },
        {
            "id": 4866,
            "comment": "[上課形式]\n1.全班分成三組上課，每組會有各自的課表並由不同的老師授課，每三堂課會換一次老師，每個老師準備的題材都不同\n2.主要以英文授課，不過有些老師是中英搭配\n3.沒有點名，但因為分組分班上課後人數很少，老師比較容易發現有人沒到\n\n[評分方式]\n1.每個老師的評分標準都不同但都還不錯\n2.沒有期中和期末考\n3.作業: 每個老師都不同，我遇到的有上台說英文笑話、拍一部殭屍英文微電影、有關運動的英文報告。幸運的話，有些老師不會給作業\n\n整體來說，不排斥英文的話，這堂課是還蠻輕鬆的，接觸到的東西也很豐富或是說很雜，就看遇到怎樣的老師囉",
            "semester": "107-1"
        },
        {
            "id": 4342,
            "comment": "[上課形式]\n1. 全班分成三大組，每三周換一位老師，一個老師上三周課。\n2. 英文授課，有些老師會希望連課中小討論都用英文。\n3. 上課通常有搭配投影片，也有老師直接講課。\n\n[評分方式]\n1. 通常每個老師的最後一周會有報告或是一些會被評分的活動。(有些老師感覺沒有在打分數，所以也不知道標準是啥XD)\n\n[作業考試]\n1. 無考試\n2. 作業形式很多：準備一個故事(英文)上台講、兩人一組展演USMLE醫生病患對話、拍影片，其他是不同組題的分組報告。",
            "semester": "107-1"
        }
    ],
    "rates": [
        {
            "id": 1761,
            "got": 7,
            "sweet": 10,
            "cold": 6,
            "user_id": 2265,
            "post_id": 4342,
            "course_name": "全球視野與溝通",
            "teacher": "張嘉倩 石明人 林呈鳳 張雋曦*陳韻雯 姜學誠 王淑鶯 黃一修 彭貴春 林明彥",
            "like": 0,
            "dislike": 0,
            "give": 1,
            "recommand": 1,
            "hard": 1
        },
        {
            "id": 2285,
            "got": 8,
            "sweet": 9,
            "cold": 7,
            "user_id": 2494,
            "post_id": 4866,
            "course_name": "全球視野與溝通",
            "teacher": "張嘉倩 石明人 林呈鳳 張雋曦*陳韻雯 姜學誠 王淑鶯 黃一修 彭貴春 林明彥",
            "like": 0,
            "dislike": 0,
            "give": 1,
            "recommand": 1,
            "hard": 1
        },
        {
            "id": 3812,
            "got": 4,
            "sweet": 8,
            "cold": 7,
            "user_id": 1742,
            "post_id": 6441,
            "course_name": "全球視野與溝通",
            "teacher": "張嘉倩 石明人 林呈鳳 張雋曦*陳韻雯 姜學誠 王淑鶯 黃一修 彭貴春 林明彥",
            "like": 0,
            "dislike": 0,
            "give": 1,
            "recommand": 1,
            "hard": 1
        },
        {
            "id": 4000,
            "got": 8,
            "sweet": 9,
            "cold": 6,
            "user_id": 3489,
            "post_id": 6629,
            "course_name": "全球視野與溝通",
            "teacher": "張嘉倩 石明人 張雋曦*陳韻雯 姜學誠 彭貴春 林明彥 橋本昌征 古鯉榕",
            "like": 0,
            "dislike": 0,
            "give": 1,
            "recommand": 1,
            "hard": 1
        },
        {
            "id": 4218,
            "got": 7,
            "sweet": 9,
            "cold": 9,
            "user_id": 4039,
            "post_id": 6847,
            "course_name": "全球視野與溝通",
            "teacher": "張嘉倩 石明人 張雋曦*陳韻雯 姜學誠 彭貴春 林明彥 橋本昌征 古鯉榕",
            "like": 0,
            "dislike": 0,
            "give": 1,
            "recommand": 1,
            "hard": 1
        },
        {
            "id": 4587,
            "got": 6,
            "sweet": 8,
            "cold": 10,
            "user_id": 5595,
            "post_id": 7337,
            "course_name": "全球視野與溝通",
            "teacher": "張雋曦*,張嘉倩,石明人,陳韻雯,姜學誠,彭貴春,林明彥,橋本昌征,古鯉榕",
            "like": 0,
            "dislike": 0,
            "give": 1,
            "recommand": 1,
            "hard": 1
        },
        {
            "id": 4596,
            "got": 6,
            "sweet": 7,
            "cold": 10,
            "user_id": 5234,
            "post_id": 7346,
            "course_name": "全球視野與溝通",
            "teacher": "張雋曦*,張嘉倩,石明人,陳韻雯,姜學誠,彭貴春,林明彥,橋本昌征,古鯉榕",
            "like": 0,
            "dislike": 0,
            "give": 1,
            "recommand": 1,
            "hard": 1
        },
        {
            "id": 5000,
            "got": 6,
            "sweet": 10,
            "cold": 8,
            "user_id": 6275,
            "post_id": 7750,
            "course_name": "全球視野與溝通",
            "teacher": "張雋曦*,吳馬丁,張嘉倩,石明人,陳韻雯,姜學誠,林明彥,蔣輯武,橋本昌征,古鯉榕",
            "like": 0,
            "dislike": 0,
            "give": 1,
            "recommand": 1,
            "hard": 1
        }
    ],
    "courserate_id": 0
}