{
    "got": "0.0",
    "cold": "0.0",
    "sweet": "0.0",
    "rate_count": 0,
    "courseInfo": {
        "id": "2915",
        "系所名稱": "建築所 ARCH",
        "系號": "N7",
        "選課序號": "N7046",
        "課程碼": "N75C500",
        "分班碼": "",
        "班別": "碩博",
        "年級": "",
        "類別": "講義",
        "組別": null,
        "英語授課": "N",
        "課程名稱": "建築理論建構與實踐",
        "選必修": "選修",
        "學分": 3,
        "老師": "宋立文*",
        "已選課人數": 7,
        "餘額": 23,
        "時間": "[3]6~8",
        "教室": "",
        "備註": "除了科技藝術學位學程的同學外，其他同學需已修畢或同時選修建築史之研究方法",
        "限選條件": "",
        "業界參與": "否",
        "屬性碼": "ARCH7311",
        "跨領域學分學程": "",
        "Moocs": "否",
        "updateTime": null,
        "comment_num": 0,
        "remain_update_time": "2021-08-08T19:40:57.000Z",
        "count": 2,
        "admit": null,
        "comment": 0,
        "course_style": 0,
        "report_hw": 0,
        "score_style": 0
    },
    "comment": [],
    "rates": [],
    "courserate_id": 0
}