{
    "got": "0.0",
    "cold": "0.0",
    "sweet": "0.0",
    "rate_count": 0,
    "courseInfo": {
        "id": 10872,
        "系所名稱": "運算碩士學程 ICM",
        "系號": "NN",
        "選課序號": "NN004",
        "課程碼": "P970900",
        "分班碼": "",
        "班別": "碩博",
        "年級": "",
        "類別": "講義",
        "組別": null,
        "英語授課": "Y",
        "課程名稱": "工業4.1:零缺陷的智慧製造",
        "選必修": "選修",
        "學分": 3,
        "老師": "鄭芳田",
        "已選課人數": 16,
        "餘額": 84,
        "時間": "[4]B~D ",
        "教室": "照坤精密儀器大樓 95405",
        "備註": "製造所、資訊所、智慧製造學位學程、半導體學院、敏求學院合班，英語授課。",
        "限選條件": "",
        "業界參與": "否",
        "屬性碼": "IMIS7215",
        "跨領域學分學程": "",
        "Moocs": "否",
        "updateTime": null,
        "comment_num": 0,
        "remain_update_time": "2022-07-18T19:21:55.000Z",
        "count": 5,
        "admit": null,
        "comment": 0,
        "course_style": 0,
        "report_hw": 0,
        "score_style": 0
    },
    "comment": [],
    "rates": [],
    "courserate_id": 0
}