{
    "got": "0.0",
    "cold": "0.0",
    "sweet": "0.0",
    "rate_count": 0,
    "courseInfo": {
        "id": 4473,
        "系所名稱": "譯農博士學程 TAS",
        "系號": "Z5",
        "選課序號": "Z5009",
        "課程碼": "Z570600",
        "分班碼": "",
        "班別": "碩博",
        "年級": "",
        "類別": "講義",
        "組別": null,
        "英語授課": "Y",
        "課程名稱": "轉譯農學特論",
        "選必修": "必修",
        "學分": 2,
        "老師": "三村徹郎*,詹明才*,方素瓊,山田昌史,林哲揚,高木優,林耀正,劉明容,劉景煌",
        "已選課人數": 0,
        "餘額": 9,
        "時間": "",
        "教室": "",
        "備註": "",
        "限選條件": "",
        "業界參與": "是",
        "屬性碼": "TAS9191",
        "跨領域學分學程": "",
        "Moocs": "否",
        "updateTime": null,
        "comment_num": 0,
        "remain_update_time": "2022-07-11T07:27:58.000Z",
        "count": 53,
        "admit": null,
        "comment": 0,
        "course_style": 0,
        "report_hw": 0,
        "score_style": 0
    },
    "comment": [],
    "rates": [],
    "courserate_id": 0
}